sqlimit/SQlimit.py
sqlimit/__init__.py
sqlimit/_version.py
sqlimit/data/ASTMG173.csv
sqlimit/data/SQ limit.csv
sqlimit-0.0.1.post1.dist-info/METADATA
sqlimit-0.0.1.post1.dist-info/WHEEL
sqlimit-0.0.1.post1.dist-info/top_level.txt
sqlimit-0.0.1.post1.dist-info/RECORD
