Metadata-Version: 2.1
Name: sqlimit
Version: 0.0.1.post1
Summary: Shockley-Quiesser limit calculations.
Home-page: https://github.com/bicarlsen/Shockley-Queisser-limit
Author: Brian Carlsen <carlsen.bri@gmail.com>, C. Marcus Chuang <marcus.chchuang@gmail.com>
Author-email: carlsen.bri@gmail.com
License: UNKNOWN
Platform: UNKNOWN
Classifier: Programming Language :: Python :: 3
Classifier: License :: OSI Approved :: MIT License
Classifier: Operating System :: OS Independent
Requires-Dist: numpy
Requires-Dist: pandas
Requires-Dist: matplotlib
Requires-Dist: scipy
